llm_anyscale_endpoints.py
llm_anyscale_endpoints-0.6.dist-info/LICENSE
llm_anyscale_endpoints-0.6.dist-info/METADATA
llm_anyscale_endpoints-0.6.dist-info/WHEEL
llm_anyscale_endpoints-0.6.dist-info/entry_points.txt
llm_anyscale_endpoints-0.6.dist-info/top_level.txt
llm_anyscale_endpoints-0.6.dist-info/RECORD
