Metadata-Version: 2.1
Name: llm-anyscale-endpoints
Version: 0.6
Summary: LLM plugin for models hosted by Anyscale Endpoints
Author: Simon Willison
License: Apache-2.0
Project-URL: Homepage, https://github.com/simonw/llm-anyscale-endpoints
Project-URL: Changelog, https://github.com/simonw/llm-anyscale-endpoints/releases
Project-URL: Issues, https://github.com/simonw/llm-anyscale-endpoints/issues
Project-URL: CI, https://github.com/simonw/llm-anyscale-endpoints/actions
Classifier: License :: OSI Approved :: Apache Software License
License-File: LICENSE
Requires-Dist: llm >=0.8
Provides-Extra: test
Requires-Dist: pytest ; extra == 'test'
Requires-Dist: pytest-httpx ; extra == 'test'
